ntec/Classifiers.py
ntec/__init__.py
ntec/clean_name.py
ntec/models/joeg/joeg_architecture.json
ntec/models/joeg/joeg_classes.json
ntec/models/joeg/joeg_params.json
ntec/models/joeg/joeg_weights.h5
ntec-0.1.0.dist-info/LICENSE
ntec-0.1.0.dist-info/METADATA
ntec-0.1.0.dist-info/WHEEL
ntec-0.1.0.dist-info/top_level.txt
ntec-0.1.0.dist-info/RECORD
