Metadata-Version: 2.1
Name: ntec
Version: 0.1.0
Summary: Ethnicity classification based on names.
Author-email: Matthias Nigggli <matthiasniggli@gmx.ch>
License: MIT License
Project-URL: Homepage, https://github.com/matthnig/ntec
Project-URL: Paper, https://academic.oup.com/joeg/advance-article/doi/10.1093/jeg/lbad001/7010698?utm_source=authortollfreelink&utm_campaign=joeg&utm_medium=email&guestAccessKey=431e97d4-c455-49ab-9019-d622f648c6d5
Keywords: name classification,ethnicity classification
Classifier: Development Status :: 3 - Alpha
Classifier: Intended Audience :: Science/Research
Classifier: License :: OSI Approved :: MIT License
Classifier: Programming Language :: Python :: 3
Classifier: Programming Language :: Python :: 3.9
Classifier: Natural Language :: English
Classifier: Topic :: Scientific/Engineering :: Artificial Intelligence
Classifier: Topic :: Scientific/Engineering :: Information Analysis
Classifier: Topic :: Text Processing
Classifier: Topic :: Text Processing :: Linguistic
Requires-Python: >=3.7
License-File: LICENSE
Requires-Dist: numpy
Requires-Dist: pandas
Requires-Dist: unidecode
Provides-Extra: test
Requires-Dist: pytest ; extra == 'test'
